images/console-access.png
images/ome-tiff-with-metadata-viewer.png
images/scene-selection.gif
images/tiled-czi.png
images/tiled-lif.png
napari_aicsimageio/__init__.py
napari_aicsimageio/core.py
napari_aicsimageio/napari.yaml
napari_aicsimageio/tests/conftest.py
napari_aicsimageio/tests/test_core.py
napari_aicsimageio-0.7.2.dist-info/LICENSE
napari_aicsimageio-0.7.2.dist-info/METADATA
napari_aicsimageio-0.7.2.dist-info/WHEEL
napari_aicsimageio-0.7.2.dist-info/entry_points.txt
napari_aicsimageio-0.7.2.dist-info/top_level.txt
napari_aicsimageio-0.7.2.dist-info/RECORD
