Metadata-Version: 2.1
Name: napari-aicsimageio
Version: 0.7.2
Summary: AICSImageIO bindings for napari
Author-email: Eva Maxfield Brown <evamaxfieldbrown@gmail.com>, Talley Lambert <talley.lambert@gmail.com>
License: GPLv3
Project-URL: Homepage, https://github.com/AllenCellModeling/napari-aicsimageio
Project-URL: Bug Tracker, https://github.com/AllenCellModeling/napari-aicsimageio/issues
Project-URL: Documentation, https://github.com/AllenCellModeling/napari-aicsimageio#README.md
Project-URL: User Support, https://github.com/AllenCellModeling/napari-aicsimageio/issues
Keywords: aicsimageio,CZI,image reading,imageio,LIF,metadata,napari,ND2,TIFF
Classifier: Development Status :: 5 - Production/Stable
Classifier: Intended Audience :: Science/Research
Classifier: Framework :: napari
Classifier: License :: OSI Approved :: GNU General Public License v3 (GPLv3)
Classifier: Operating System :: OS Independent
Classifier: Programming Language :: Python :: 3
Classifier: Programming Language :: Python :: 3.8
Classifier: Programming Language :: Python :: 3.9
Classifier: Programming Language :: Python :: 3.10
Classifier: Topic :: Scientific/Engineering :: Bio-Informatics
Classifier: Topic :: Scientific/Engineering :: Image Processing
Classifier: Topic :: Scientific/Engineering :: Information Analysis
Classifier: Topic :: Scientific/Engineering :: Visualization
Classifier: Topic :: Scientific/Engineering
Requires-Python: >=3.8
License-File: LICENSE
Requires-Dist: aicsimageio[all] (>=4.6.3)
Requires-Dist: fsspec[http] (>=2022.7.1)
Requires-Dist: napari (>=0.4.11)
Requires-Dist: psutil (>=5.7.0)
Requires-Dist: aicspylibczi (>=3.0.5)
Requires-Dist: bioformats-jar
Requires-Dist: readlif (>=0.6.4)
Provides-Extra: dev
Requires-Dist: black (>=19.10b0) ; extra == 'dev'
Requires-Dist: coverage (>=5.1) ; extra == 'dev'
Requires-Dist: docutils (<0.16,>=0.10) ; extra == 'dev'
Requires-Dist: flake8-debugger (>=3.2.1) ; extra == 'dev'
Requires-Dist: flake8-pyprojecttoml ; extra == 'dev'
Requires-Dist: flake8 (>=3.8.3) ; extra == 'dev'
Requires-Dist: ipython (>=7.15.0) ; extra == 'dev'
Requires-Dist: isort (>=5.7.0) ; extra == 'dev'
Requires-Dist: mypy (>=0.800) ; extra == 'dev'
Requires-Dist: pytest-runner (>=5.2) ; extra == 'dev'
Requires-Dist: twine (>=3.1.1) ; extra == 'dev'
Requires-Dist: wheel (>=0.34.2) ; extra == 'dev'
Provides-Extra: test
Requires-Dist: PyQt5 ; extra == 'test'
Requires-Dist: pytest (>=5.4.3) ; extra == 'test'
Requires-Dist: pytest-qt (~=4.0) ; extra == 'test'
Requires-Dist: pytest-cov (>=2.9.0) ; extra == 'test'
Requires-Dist: pytest-raises (>=0.11) ; extra == 'test'
Requires-Dist: pytest-xvfb (~=2.0) ; extra == 'test'
Requires-Dist: quilt3 (~=3.4.0) ; extra == 'test'
